s3lite/__init__.py
s3lite/auth.py
s3lite/bucket.py
s3lite/client.py
s3lite/exceptions.py
s3lite/object.py
s3lite/utils.py
s3lite-0.1.11.dist-info/LICENSE
s3lite-0.1.11.dist-info/METADATA
s3lite-0.1.11.dist-info/WHEEL
s3lite-0.1.11.dist-info/RECORD
