Metadata-Version: 2.1
Name: s3lite
Version: 0.1.11
Summary: Minimal async s3 implementation.
Author: RuslanUC
Author-email: dev_ruslan_uc@protonmail.com
Requires-Python: >=3.9,<4.0
Classifier: Programming Language :: Python :: 3
Classifier: Programming Language :: Python :: 3.9
Classifier: Programming Language :: Python :: 3.10
Classifier: Programming Language :: Python :: 3.11
Classifier: Programming Language :: Python :: 3.12
Requires-Dist: httpx (>=0.28.1,<0.29.0)
Requires-Dist: python-dateutil (>=2.9.0,<3.0.0)
